allennlp_srl_bert/__init__.py
allennlp_srl_bert/common/__init__.py
allennlp_srl_bert/common/cached_transformers.py
allennlp_srl_bert/common/checks.py
allennlp_srl_bert/common/file_utils.py
allennlp_srl_bert/common/from_params.py
allennlp_srl_bert/common/lazy.py
allennlp_srl_bert/common/logging.py
allennlp_srl_bert/common/meta.py
allennlp_srl_bert/common/ontonotes.py
allennlp_srl_bert/common/params.py
allennlp_srl_bert/common/plugins.py
allennlp_srl_bert/common/registrable.py
allennlp_srl_bert/common/tqdm.py
allennlp_srl_bert/common/util.py
allennlp_srl_bert/data/__init__.py
allennlp_srl_bert/data/batch.py
allennlp_srl_bert/data/instance.py
allennlp_srl_bert/data/vocabulary.py
allennlp_srl_bert/data/data_loaders/__init__.py
allennlp_srl_bert/data/data_loaders/data_collator.py
allennlp_srl_bert/data/data_loaders/data_loader.py
allennlp_srl_bert/data/data_loaders/multiprocess_data_loader.py
allennlp_srl_bert/data/dataset_readers/__init__.py
allennlp_srl_bert/data/dataset_readers/babi.py
allennlp_srl_bert/data/dataset_readers/dataset_reader.py
allennlp_srl_bert/data/dataset_readers/srl.py
allennlp_srl_bert/data/dataset_readers/dataset_utils/__init__.py
allennlp_srl_bert/data/dataset_readers/dataset_utils/span_utils.py
allennlp_srl_bert/data/fields/__init__.py
allennlp_srl_bert/data/fields/field.py
allennlp_srl_bert/data/fields/index_field.py
allennlp_srl_bert/data/fields/list_field.py
allennlp_srl_bert/data/fields/metadata_field.py
allennlp_srl_bert/data/fields/sequence_field.py
allennlp_srl_bert/data/fields/sequence_label_field.py
allennlp_srl_bert/data/fields/text_field.py
allennlp_srl_bert/data/samplers/__init__.py
allennlp_srl_bert/data/samplers/batch_sampler.py
allennlp_srl_bert/data/token_indexers/__init__.py
allennlp_srl_bert/data/token_indexers/pretrained_transformer_indexer.py
allennlp_srl_bert/data/token_indexers/single_id_token_indexer.py
allennlp_srl_bert/data/token_indexers/token_indexer.py
allennlp_srl_bert/data/tokenizers/__init__.py
allennlp_srl_bert-0.1.1.dist-info/METADATA
allennlp_srl_bert-0.1.1.dist-info/WHEEL
allennlp_srl_bert-0.1.1.dist-info/top_level.txt
allennlp_srl_bert-0.1.1.dist-info/RECORD
