Metadata-Version: 2.1
Name: allennlp_srl_bert
Version: 0.1.1
Summary: Semantic Role Labeling using AllenNLP trained BERT model
Home-page: https://github.com/WGU-edu/allennlp_srl_bert
Author: Austin Light
Author-email: austin.light@wgu.edu
Classifier: Programming Language :: Python :: 3
Classifier: License :: OSI Approved :: MIT License
Classifier: Operating System :: OS Independent
Requires-Python: >=3.7
Requires-Dist: torch
Requires-Dist: cached_path
Requires-Dist: lmdb
Requires-Dist: dill
Requires-Dist: spacy
Requires-Dist: base58
Requires-Dist: transformers
Requires-Dist: nltk
Requires-Dist: jsonnet
